feedflow/__init__.py
feedflow/db.py
feedflow/logo.png
feedflow/main.py
feedflow/rss_engine.py
feedflow/utils.py
feedflow-2.0.1.dist-info/METADATA
feedflow-2.0.1.dist-info/WHEEL
feedflow-2.0.1.dist-info/entry_points.txt
feedflow-2.0.1.dist-info/licenses/LICENSE
feedflow-2.0.1.dist-info/RECORD
