Metadata-Version: 2.4
Name: feedflow
Version: 2.0.1
Summary: A stdio MCP server to manage and read RSS feeds directly from AI clients.
Project-URL: Homepage, https://github.com/geckod22/FeedFlow
Project-URL: Repository, https://github.com/geckod22/FeedFlow
Project-URL: Issues, https://github.com/geckod22/FeedFlow/issues
Author-email: Armando Liccardo <li.armando82@gmail.com>
License-Expression: MIT
License-File: LICENSE
Keywords: feed,mcp,model-context-protocol,rss
Requires-Python: >=3.13
Requires-Dist: aiosqlite>=0.22.1
Requires-Dist: fastmcp>=2.14.2
Requires-Dist: feedparser>=6.0.12
Requires-Dist: httpx>=0.28.1
Requires-Dist: langdetect>=1.0.9
